[
  {
    "name": "John Doe",
    "task": "Development",
    "hours": 5,
    "date": "2023-01-10"
  },
  {
    "name": "Jane Smith",
    "task": "Design",
    "hours": 3,
    "date": "2023-01-11"
  },
  {
    "name": "Bob Johnson",
    "task": "Testing",
    "hours": 4,
    "date": "2023-01-12"
  },
  {
    "name": "Alice Williams",
    "task": "Support",
    "hours": 6,
    "date": "2023-01-13"
  },
  {
    "name": "Charlie Brown",
    "task": "Documentation",
    "hours": 2,
    "date": "2023-01-14"
  }
]
